INSTALL.rst
LICENSE
MANIFEST.in
README.rst
VERSION
requirements.txt
setup.py
tasks.py
src/ni/__init__.py
src/ni/converter.py
src/ni/to_ast.py
src/pyml/__init__.py
src/pyml/conftest.py
src/pyml/css.py
src/pyml/errors.py
src/pyml/jinja2.py
src/pyml/json.py
src/pyml/tags.py
src/pyml/components/__init__.py
src/pyml/components/attrs.py
src/pyml/components/children.py
src/pyml/components/core.py
src/pyml/components/data_components.py
src/pyml/components/mixins.py
src/pyml/components/text.py
src/pyml/components/ugly.py
src/pyml/helpers/__init__.py
src/pyml/helpers/attr.py
src/pyml/helpers/extras.py
src/pyml/helpers/hyperlink.py
src/pyml/helpers/render.py
src/pyml/helpers/utils.py
src/pyml/require/__init__.py
src/pyml/require/asset_manager.py
src/pyml/require/base_assets.py
src/pyml/require/data_assets.py
src/pyml/require/lib.py
src/pyml/require/requirable.py
src/pyml/require/utils.py
src/pyml/tests/__init__.py
src/pyml/tests/test_components.py
src/pyml/tests/test_css.py
src/pyml/tests/test_helpers.py
src/pyml/tests/test_pyml.py
src/pyml/tests/test_requires.py
src/pyml/utils/__init__.py
src/pyml/utils/generic.py
src/pyml/utils/random.py
src/pyml/utils/string.py
src/srvice/__init__.py
src/srvice/__main__.py
src/srvice/__meta__.py
src/srvice/admin.py
src/srvice/apps.py
src/srvice/client.py
src/srvice/decorators.py
src/srvice/exceptions.py
src/srvice/json.py
src/srvice/models.py
src/srvice/sysviews.py
src/srvice/urls.py
src/srvice/views.py
src/srvice.egg-info/PKG-INFO
src/srvice.egg-info/SOURCES.txt
src/srvice.egg-info/dependency_links.txt
src/srvice.egg-info/not-zip-safe
src/srvice.egg-info/requires.txt
src/srvice.egg-info/top_level.txt
src/srvice/migrations/__init__.py
src/srvice/static/js/srvice/actions.js
src/srvice/static/js/srvice/commands.js
src/srvice/static/js/srvice/core.js
src/srvice/static/js/srvice/dialog.js
src/srvice/static/js/srvice/django_object.js
src/srvice/static/js/srvice/json.js
src/srvice/static/js/srvice/util.js
src/srvice/tests/__init__.py
src/srvice/tests/__main__.py
src/srvice/tests/test_client.py
src/srvice/tests/test_documentation.py